scip/__init__.py
scip/_version.py
scip/main.py
scip/export/__init__.py
scip/export/anndata.py
scip/export/parquet.py
scip/features/__init__.py
scip/features/bbox.py
scip/features/intensity.py
scip/features/raw_intensity.py
scip/features/shape.py
scip/features/texture.py
scip/filter/__init__.py
scip/filter/threshold.py
scip/illumination_correction/__init__.py
scip/illumination_correction/jones_2006.py
scip/loading/__init__.py
scip/loading/czi.py
scip/loading/multiframe_tiff.py
scip/loading/tiff.py
scip/loading/util.py
scip/loading/zarr.py
scip/masking/__init__.py
scip/masking/circle.py
scip/masking/li.py
scip/masking/otsu.py
scip/masking/sobel.py
scip/masking/spot.py
scip/masking/watershed.py
scip/masking/filters/__init__.py
scip/masking/filters/normaltest.py
scip/masking/filters/std.py
scip/masking/filters/value_range.py
scip/normalization/__init__.py
scip/normalization/quantile_normalization.py
scip/projection/__init__.py
scip/projection/op.py
scip/segmentation/__init__.py
scip/segmentation/cellpose.py
scip/segmentation/watershed_dapi.py
scip/utils/__init__.py
scip/utils/logging.yml
scip/utils/util.py
scip-0.1.12.dist-info/LICENSE
scip-0.1.12.dist-info/METADATA
scip-0.1.12.dist-info/WHEEL
scip-0.1.12.dist-info/entry_points.txt
scip-0.1.12.dist-info/top_level.txt
scip-0.1.12.dist-info/RECORD
